pycircleci/__init__.py
pycircleci/api.py
pycircleci/console.py
tests/__init__.py
tests/test_api.py
pycircleci-0.7.0.dist-info/LICENSE
pycircleci-0.7.0.dist-info/METADATA
pycircleci-0.7.0.dist-info/WHEEL
pycircleci-0.7.0.dist-info/top_level.txt
pycircleci-0.7.0.dist-info/RECORD
