Metadata-Version: 2.1
Name: pycircleci
Version: 0.7.0
Summary: Python client for CircleCI API
Home-page: https://github.com/alpinweis/pycircleci
Author: Adrian Kazaku
Author-email: alpinweis@gmail.com
License: MIT
Keywords: circleci ci cd api
Platform: UNKNOWN
Classifier: Development Status :: 5 - Production/Stable
Classifier: Intended Audience :: Developers
Classifier: Intended Audience :: System Administrators
Classifier: License :: OSI Approved :: MIT License
Classifier: Operating System :: OS Independent
Classifier: Topic :: Software Development :: Build Tools
Classifier: Topic :: Software Development :: Libraries :: Python Modules
Classifier: Topic :: Internet
Classifier: Programming Language :: Python :: 3
Classifier: Programming Language :: Python :: 3.8
Classifier: Programming Language :: Python :: 3.9
Classifier: Programming Language :: Python :: 3.10
Classifier: Programming Language :: Python :: 3.11
Classifier: Programming Language :: Python :: 3 :: Only
Requires-Python: >=3.6
Requires-Dist: requests
Requires-Dist: requests-toolbelt
